{
  "status": "ok",
  "timezone": "Asia/Taipei",
  "updated_at": "2026-04-28T14:38:59.334113+08:00",
  "groups": [
    {
      "label": "Asia",
      "count": 4,
      "active": 4,
      "items": [
        {
          "symbol": "^TWII",
          "name": "Taiwan",
          "group": "Asia",
          "price": 39521.73,
          "change": -94.9,
          "change_percent": -0.24,
          "direction": "down",
          "updated_at": "2026-04-28T14:38:59.106127+08:00",
          "timezone": "Asia/Taipei",
          "source": "yfinance",
          "status": "ok"
        },
        {
          "symbol": "^N225",
          "name": "Japan",
          "group": "Asia",
          "price": 59837.22,
          "change": -700.14,
          "change_percent": -1.16,
          "direction": "down",
          "updated_at": "2026-04-28T14:38:59.146540+08:00",
          "timezone": "Asia/Taipei",
          "source": "yfinance",
          "status": "ok"
        },
        {
          "symbol": "^KS11",
          "name": "Korea",
          "group": "Asia",
          "price": 6643.78,
          "change": 28.75,
          "change_percent": 0.43,
          "direction": "up",
          "updated_at": "2026-04-28T14:38:59.165380+08:00",
          "timezone": "Asia/Taipei",
          "source": "yfinance",
          "status": "ok"
        },
        {
          "symbol": "^HSI",
          "name": "Hong Kong",
          "group": "Asia",
          "price": 25638.7,
          "change": -286.95,
          "change_percent": -1.11,
          "direction": "down",
          "updated_at": "2026-04-28T14:38:59.144689+08:00",
          "timezone": "Asia/Taipei",
          "source": "yfinance",
          "status": "ok"
        }
      ]
    },
    {
      "label": "USA",
      "count": 3,
      "active": 3,
      "items": [
        {
          "symbol": "^GSPC",
          "name": "S&P 500",
          "group": "USA",
          "price": 7173.91,
          "change": 8.83,
          "change_percent": 0.12,
          "direction": "up",
          "updated_at": "2026-04-28T14:38:59.153311+08:00",
          "timezone": "Asia/Taipei",
          "source": "yfinance",
          "status": "ok"
        },
        {
          "symbol": "^IXIC",
          "name": "Nasdaq",
          "group": "USA",
          "price": 24887.1,
          "change": 50.5,
          "change_percent": 0.2,
          "direction": "up",
          "updated_at": "2026-04-28T14:38:59.160251+08:00",
          "timezone": "Asia/Taipei",
          "source": "yfinance",
          "status": "ok"
        },
        {
          "symbol": "^SOX",
          "name": "PHLX Semiconductor",
          "group": "USA",
          "price": 10408.04,
          "change": -105.62,
          "change_percent": -1.0,
          "direction": "down",
          "updated_at": "2026-04-28T14:38:59.115457+08:00",
          "timezone": "Asia/Taipei",
          "source": "yfinance",
          "status": "ok"
        }
      ]
    },
    {
      "label": "Commodities",
      "count": 3,
      "active": 3,
      "items": [
        {
          "symbol": "GC=F",
          "name": "Gold",
          "group": "Commodities",
          "price": 4646.2,
          "change": -29.2,
          "change_percent": -0.62,
          "direction": "down",
          "updated_at": "2026-04-28T14:38:59.108815+08:00",
          "timezone": "Asia/Taipei",
          "source": "yfinance",
          "status": "ok"
        },
        {
          "symbol": "BZ=F",
          "name": "Brent Oil",
          "group": "Commodities",
          "price": 103.2,
          "change": -5.03,
          "change_percent": -4.65,
          "direction": "down",
          "updated_at": "2026-04-28T14:38:59.312552+08:00",
          "timezone": "Asia/Taipei",
          "source": "yfinance",
          "status": "ok"
        },
        {
          "symbol": "CL=F",
          "name": "WTI Oil",
          "group": "Commodities",
          "price": 97.96,
          "change": 1.59,
          "change_percent": 1.65,
          "direction": "up",
          "updated_at": "2026-04-28T14:38:59.333411+08:00",
          "timezone": "Asia/Taipei",
          "source": "yfinance",
          "status": "ok"
        }
      ]
    }
  ]
}